MANIFEST.in
README.rst
setup.cfg
setup.py
microsip_envia_sms/__init__.py
microsip_envia_sms/__init__.pyc
microsip_envia_sms/configuracion.exe
microsip_envia_sms/send_message.pyc
microsip_envia_sms/settings.pyc
microsip_envia_sms.egg-info/PKG-INFO
microsip_envia_sms.egg-info/SOURCES.txt
microsip_envia_sms.egg-info/dependency_links.txt
microsip_envia_sms.egg-info/top_level.txt
microsip_envia_sms/modules/__init__.py
microsip_envia_sms/modules/__init__.pyc
microsip_envia_sms/modules/bill_message.pyc