Metadata-Version: 1.1
Name: microsip-envia-sms
Version: 0.0.12
Summary: Envia SMS sobre acciones de Microsip
Home-page: UNKNOWN
Author: Servicios de Ingenieria Computacional
Author-email: felixfhdez15@gmail.com
License: BSD License
Platform: UNKNOWN
Classifier: Environment :: Web Environment
Classifier: Framework :: Django
Classifier: Intended Audience :: Developers
Classifier: License :: OSI Approved :: BSD License
Classifier: Operating System :: OS Independent
Classifier: Programming Language :: Python
Classifier: Programming Language :: Python :: 2.6
Classifier: Programming Language :: Python :: 2.7
Classifier: Topic :: Internet :: WWW/HTTP
Classifier: Topic :: Internet :: WWW/HTTP :: Dynamic Content
